data/Emoji_Sentiment_Data_v1.0.csv
data/Emoji_Sentiment_Data_v2.0.csv
data/__init__.py
data/emoticon.py
data/func.py
data/modifier.py
msiaLex/__init__.py
msiaLex/emoticon.py
msiaLex/func.py
msiaLex/modifier.py
msiaLex/data/__init__.py
tests/__init__.py
tests/test_modifier.py
msiaLex-0.3.9.19.dist-info/LICENSE.txt
msiaLex-0.3.9.19.dist-info/METADATA
msiaLex-0.3.9.19.dist-info/WHEEL
msiaLex-0.3.9.19.dist-info/top_level.txt
msiaLex-0.3.9.19.dist-info/RECORD
