Metadata-Version: 2.1
Name: msiaLex
Version: 0.3.9.19
Summary: Malaysia Lexicon
Home-page: https://github.com/yuenkeiwac/msialex
Author: Khor Yuen Kei
Author-email: khoryk1104@gmail.com
License: MIT
License-File: LICENSE.txt
